{
    "nodes": [
        {
            "name": "Albus Dumbledore",
            "gender": "M",
            "group": 1,
            "index": 0
        },
        {
            "name": "Albus Severus Potter",
            "gender": "M",
            "group": 1,
            "index": 1
        },
        {
            "name": "Alice Longbottom",
            "gender": "F",
            "group": 1,
            "index": 2
        },
        {
            "name": "Andromeda Black Tonks",
            "gender": "F",
            "group": 1,
            "index": 3
        },
        {
            "name": "Angelina Johnson",
            "gender": "F",
            "group": 1,
            "index": 4
        },
        {
            "name": "Arthur Weasley",
            "gender": "M",
            "group": 1,
            "index": 5
        },
        {
            "name": "Astoria Greengrass",
            "gender": "F",
            "group": 1,
            "index": 6
        },
        {
            "name": "Barty Crouch Jr.",
            "gender": "M",
            "group": 1,
            "index": 7
        },
        {
            "name": "Bellatrix Black Lestrange",
            "gender": "F",
            "group": 1,
            "index": 8
        },
        {
            "name": "Bill Weasley",
            "gender": "M",
            "group": 1,
            "index": 9
        },
        {
            "name": "Blaise Zabini",
            "gender": "M",
            "group": 1,
            "index": 10
        },
        {
            "name": "Cedric Diggory",
            "gender": "M",
            "group": 1,
            "index": 11
        },
        {
            "name": "Daphne Greengrass",
            "gender": "F",
            "group": 1,
            "index": 12
        },
        {
            "name": "Dean Thomas",
            "gender": "M",
            "group": 1,
            "index": 13
        },
        {
            "name": "Dorcas Meadowes",
            "gender": "F",
            "group": 1,
            "index": 14
        },
        {
            "name": "Draco Malfoy",
            "gender": "M",
            "group": 1,
            "index": 15
        },
        {
            "name": "Evan Rosier",
            "gender": "M",
            "group": 1,
            "index": 16
        },
        {
            "name": "Fleur Delacour",
            "gender": "F",
            "group": 1,
            "index": 17
        },
        {
            "name": "Frank Longbottom",
            "gender": "M",
            "group": 1,
            "index": 18
        },
        {
            "name": "Fred Weasley",
            "gender": "M",
            "group": 1,
            "index": 19
        },
        {
            "name": "Gellert Grindelwald",
            "gender": "M",
            "group": 1,
            "index": 20
        },
        {
            "name": "George Weasley",
            "gender": "M",
            "group": 1,
            "index": 21
        },
        {
            "name": "Ginny Weasley",
            "gender": "F",
            "group": 1,
            "index": 22
        },
        {
            "name": "Hannah Abbott",
            "gender": "F",
            "group": 1,
            "index": 23
        },
        {
            "name": "Harry Potter",
            "gender": "M",
            "group": 1,
            "index": 24
        },
        {
            "name": "Hermione Granger",
            "gender": "F",
            "group": 1,
            "index": 25
        },
        {
            "name": "Jacob Kowalski",
            "gender": "M",
            "group": 1,
            "index": 26
        },
        {
            "name": "James Potter",
            "gender": "M",
            "group": 1,
            "index": 27
        },
        {
            "name": "Lavender Brown",
            "gender": "F",
            "group": 1,
            "index": 28
        },
        {
            "name": "Lily Evans Potter",
            "gender": "F",
            "group": 1,
            "index": 29
        },
        {
            "name": "Lucius Malfoy",
            "gender": "M",
            "group": 1,
            "index": 30
        },
        {
            "name": "Luna Lovegood",
            "gender": "F",
            "group": 1,
            "index": 31
        },
        {
            "name": "Marlene McKinnon",
            "gender": "F",
            "group": 1,
            "index": 32
        },
        {
            "name": "Mary Macdonald",
            "gender": "F",
            "group": 1,
            "index": 33
        },
        {
            "name": "Molly Weasley",
            "gender": "F",
            "group": 1,
            "index": 34
        },
        {
            "name": "Narcissa Black Malfoy",
            "gender": "F",
            "group": 1,
            "index": 35
        },
        {
            "name": "Neville Longbottom",
            "gender": "M",
            "group": 1,
            "index": 36
        },
        {
            "name": "Newt Scamander",
            "gender": "M",
            "group": 1,
            "index": 37
        },
        {
            "name": "Nymphadora Tonks",
            "gender": "F",
            "group": 1,
            "index": 38
        },
        {
            "name": "Oliver Wood",
            "gender": "M",
            "group": 1,
            "index": 39
        },
        {
            "name": "Pansy Parkinson",
            "gender": "F",
            "group": 1,
            "index": 40
        },
        {
            "name": "Percy Weasley",
            "gender": "M",
            "group": 1,
            "index": 41
        },
        {
            "name": "Peter Pettigrew",
            "gender": "M",
            "group": 1,
            "index": 42
        },
        {
            "name": "Queenie Goldstein",
            "gender": "F",
            "group": 1,
            "index": 43
        },
        {
            "name": "Regulus Black",
            "gender": "M",
            "group": 1,
            "index": 44
        },
        {
            "name": "Remus Lupin",
            "gender": "M",
            "group": 1,
            "index": 45
        },
        {
            "name": "Rodolphus Lestrange",
            "gender": "M",
            "group": 1,
            "index": 46
        },
        {
            "name": "Ron Weasley",
            "gender": "M",
            "group": 1,
            "index": 47
        },
        {
            "name": "Rose Weasley",
            "gender": "F",
            "group": 1,
            "index": 48
        },
        {
            "name": "Scorpius Malfoy",
            "gender": "M",
            "group": 1,
            "index": 49
        },
        {
            "name": "Seamus Finnigan",
            "gender": "M",
            "group": 1,
            "index": 50
        },
        {
            "name": "Sebastian Sallow",
            "gender": "M",
            "group": 1,
            "index": 51
        },
        {
            "name": "Severus Snape",
            "gender": "M",
            "group": 1,
            "index": 52
        },
        {
            "name": "Sirius Black",
            "gender": "M",
            "group": 1,
            "index": 53
        },
        {
            "name": "Ted Tonks",
            "gender": "M",
            "group": 1,
            "index": 54
        },
        {
            "name": "Teddy Lupin",
            "gender": "M",
            "group": 1,
            "index": 55
        },
        {
            "name": "Theodore Nott",
            "gender": "M",
            "group": 1,
            "index": 56
        },
        {
            "name": "Theseus Scamander",
            "gender": "M",
            "group": 1,
            "index": 57
        },
        {
            "name": "Tom Riddle | Voldemort",
            "gender": "M",
            "group": 1,
            "index": 58
        },
        {
            "name": "Victoire Weasley",
            "gender": "F",
            "group": 1,
            "index": 59
        },
        {
            "name": "Viktor Krum",
            "gender": "M",
            "group": 1,
            "index": 60
        }
    ],
    "links": [
        {
            "source": 15,
            "target": 24,
            "value": 62215,
            "relType": "M/M"
        },
        {
            "source": 53,
            "target": 45,
            "value": 44820,
            "relType": "M/M"
        },
        {
            "source": 25,
            "target": 15,
            "value": 26816,
            "relType": "F/M"
        },
        {
            "source": 29,
            "target": 27,
            "value": 24500,
            "relType": "F/M"
        },
        {
            "source": 25,
            "target": 47,
            "value": 19817,
            "relType": "F/M"
        },
        {
            "source": 24,
            "target": 22,
            "value": 16451,
            "relType": "F/M"
        },
        {
            "source": 24,
            "target": 52,
            "value": 15772,
            "relType": "M/M"
        },
        {
            "source": 24,
            "target": 58,
            "value": 11721,
            "relType": "M/M"
        },
        {
            "source": 44,
            "target": 47,
            "value": 11705,
            "relType": "M/M"
        },
        {
            "source": 25,
            "target": 52,
            "value": 8092,
            "relType": "F/M"
        },
        {
            "source": 25,
            "target": 24,
            "value": 7549,
            "relType": "F/M"
        },
        {
            "source": 32,
            "target": 14,
            "value": 7279,
            "relType": "F/F"
        },
        {
            "source": 30,
            "target": 35,
            "value": 5687,
            "relType": "F/M"
        },
        {
            "source": 0,
            "target": 20,
            "value": 4802,
            "relType": "M/M"
        },
        {
            "source": 49,
            "target": 1,
            "value": 4487,
            "relType": "M/M"
        },
        {
            "source": 45,
            "target": 38,
            "value": 4062,
            "relType": "F/M"
        },
        {
            "source": 45,
            "target": 52,
            "value": 3766,
            "relType": "M/M"
        },
        {
            "source": 7,
            "target": 16,
            "value": 3496,
            "relType": "M/M"
        },
        {
            "source": 6,
            "target": 15,
            "value": 3317,
            "relType": "F/M"
        },
        {
            "source": 24,
            "target": 47,
            "value": 3083,
            "relType": "M/M"
        },
        {
            "source": 53,
            "target": 27,
            "value": 2741,
            "relType": "M/M"
        },
        {
            "source": 29,
            "target": 52,
            "value": 2689,
            "relType": "F/M"
        },
        {
            "source": 33,
            "target": 29,
            "value": 2571,
            "relType": "F/F"
        },
        {
            "source": 53,
            "target": 52,
            "value": 2429,
            "relType": "M/M"
        },
        {
            "source": 5,
            "target": 34,
            "value": 2409,
            "relType": "F/M"
        },
        {
            "source": 50,
            "target": 13,
            "value": 2392,
            "relType": "M/M"
        },
        {
            "source": 25,
            "target": 40,
            "value": 2318,
            "relType": "F/F"
        },
        {
            "source": 25,
            "target": 19,
            "value": 2192,
            "relType": "F/M"
        },
        {
            "source": 25,
            "target": 58,
            "value": 2083,
            "relType": "F/M"
        },
        {
            "source": 17,
            "target": 9,
            "value": 2071,
            "relType": "F/M"
        },
        {
            "source": 25,
            "target": 8,
            "value": 2038,
            "relType": "F/F"
        },
        {
            "source": 36,
            "target": 31,
            "value": 2038,
            "relType": "F/M"
        },
        {
            "source": 2,
            "target": 18,
            "value": 1804,
            "relType": "F/M"
        },
        {
            "source": 15,
            "target": 22,
            "value": 1770,
            "relType": "F/M"
        },
        {
            "source": 15,
            "target": 47,
            "value": 1739,
            "relType": "M/M"
        },
        {
            "source": 31,
            "target": 24,
            "value": 1693,
            "relType": "F/M"
        },
        {
            "source": 3,
            "target": 54,
            "value": 1650,
            "relType": "F/M"
        },
        {
            "source": 25,
            "target": 56,
            "value": 1610,
            "relType": "F/M"
        },
        {
            "source": 49,
            "target": 48,
            "value": 1504,
            "relType": "F/M"
        },
        {
            "source": 56,
            "target": 24,
            "value": 1492,
            "relType": "M/M"
        },
        {
            "source": 30,
            "target": 52,
            "value": 1487,
            "relType": "M/M"
        },
        {
            "source": 41,
            "target": 39,
            "value": 1487,
            "relType": "M/M"
        },
        {
            "source": 28,
            "target": 47,
            "value": 1429,
            "relType": "F/M"
        },
        {
            "source": 53,
            "target": 25,
            "value": 1418,
            "relType": "F/M"
        },
        {
            "source": 31,
            "target": 22,
            "value": 1410,
            "relType": "F/F"
        },
        {
            "source": 36,
            "target": 40,
            "value": 1379,
            "relType": "F/M"
        },
        {
            "source": 4,
            "target": 21,
            "value": 1327,
            "relType": "F/M"
        },
        {
            "source": 40,
            "target": 24,
            "value": 1313,
            "relType": "F/M"
        },
        {
            "source": 12,
            "target": 24,
            "value": 1311,
            "relType": "F/M"
        },
        {
            "source": 25,
            "target": 30,
            "value": 1307,
            "relType": "F/M"
        },
        {
            "source": 25,
            "target": 60,
            "value": 1274,
            "relType": "F/M"
        },
        {
            "source": 17,
            "target": 25,
            "value": 1273,
            "relType": "F/F"
        },
        {
            "source": 11,
            "target": 24,
            "value": 1224,
            "relType": "M/M"
        },
        {
            "source": 22,
            "target": 10,
            "value": 1218,
            "relType": "F/F"
        },
        {
            "source": 37,
            "target": 57,
            "value": 1178,
            "relType": "M/M"
        },
        {
            "source": 30,
            "target": 24,
            "value": 1160,
            "relType": "M/M"
        },
        {
            "source": 8,
            "target": 46,
            "value": 1155,
            "relType": "F/M"
        },
        {
            "source": 53,
            "target": 24,
            "value":  1147,
            "relType": "M/M"
        },
        {
            "source": 15,
            "target": 40,
            "value":  1143,
            "relType": "F/M"
        },
        {
            "source": 43,
            "target": 26,
            "value":  1124,
            "relType": "F/M"
        },
        {
            "source": 27,
            "target": 52,
            "value": 1095,
            "relType": "M/M"
        },
        {
            "source": 23,
            "target": 36,
            "value": 1030,
            "relType": "F/M"
        },
        {
            "source": 44,
            "target": 7,
            "value": 1025,
            "relType": "M/M"
        },
        {
            "source": 55,
            "target": 59,
            "value": 1017,
            "relType": "F/M"
        },
        {
            "source": 25,
            "target": 22,
            "value": 1011,
            "relType": "F/F"
        },
        {
            "source": 40,
            "target": 47,
            "value": 1003,
            "relType": "F/M"
        }
    ]
}